MatrixPythonClient
