Metadata-Version: 2.4
Name: matrixpythonclient
Version: 0.0.46
Summary: Python package which provides Matrix Rest API Client
Home-page: https://github.com/rmetcalf9/MatrixPythonClient
Author: Robert Metcalf
Author-email: rmetcalf9@googlemail.com
License: MIT
Requires-Dist: requests==2.31.0
Requires-Dist: pytz==2025.2
Requires-Dist: python-dateutil==2.9.0.post0
Requires-Dist: PythonAPIClientBase==0.0.17
Requires-Dist: InquirerPy==0.3.4
Dynamic: author
Dynamic: author-email
Dynamic: description
Dynamic: description-content-type
Dynamic: home-page
Dynamic: license
Dynamic: requires-dist
Dynamic: summary
